{
    "@type": "Workflow",
    "triggerLimit": null,
    "name": "On Asset Creation",
    "aliasName": null,
    "tag": null,
    "description": "On Asset Creation (source Nozomi CMC) link it to existing KEV Alert (if any for same vendor).",
    "isActive": true,
    "debug": false,
    "singleRecordExecution": false,
    "remoteExecutableFlag": false,
    "parameters": [],
    "synchronous": false,
    "collection": "\/api\/3\/workflow_collections\/566483c2-686f-4c7d-b8df-eb51583b1814",
    "versions": [],
    "triggerStep": "\/api\/3\/workflow_steps\/460300eb-79e1-4d8a-8963-75e4eccdfa98",
    "steps": [
        {
            "@type": "WorkflowStep",
            "name": "Add Comment",
            "description": null,
            "arguments": {
                "when": "{{vars.steps.Get_CVEs_By_Vendor | length > 0}}",
                "resource": {
                    "type": "\/api\/3\/picklists\/ff599189-3eeb-4c86-acb0-a7915e85ac3b",
                    "assets": "{{vars.record[\"@id\"]}}",
                    "people": [],
                    "content": "<p>{{vars.steps.Summary_On_Asset.data['formatted_string']}}<\/p>",
                    "__replace": "",
                    "isImportant": false,
                    "peopleUpdated": false
                },
                "operation": "Overwrite",
                "collection": "\/api\/3\/comments",
                "__recommend": [],
                "fieldOperation": {
                    "recordTags": "Overwrite"
                },
                "step_variables": []
            },
            "status": null,
            "top": "705",
            "left": "125",
            "stepType": "\/api\/3\/workflow_step_types\/2597053c-e718-44b4-8394-4d40fe26d357",
            "group": null,
            "uuid": "b8ad6c76-96fc-4ccb-93ae-83caf52a807b"
        },
        {
            "@type": "WorkflowStep",
            "name": "Configuration",
            "description": null,
            "arguments": {
                "record": "{{vars.input.records[0]}}"
            },
            "status": null,
            "top": "165",
            "left": "125",
            "stepType": "\/api\/3\/workflow_step_types\/04d0cf46-b6a8-42c4-8683-60a7eaa69e8f",
            "group": null,
            "uuid": "0ae118b4-4f4c-488b-96f7-c694860302dc"
        },
        {
            "@type": "WorkflowStep",
            "name": "Get CVEs By Vendor",
            "description": null,
            "arguments": {
                "query": {
                    "sort": [],
                    "limit": 30,
                    "logic": "AND",
                    "filters": [
                        {
                            "type": "array",
                            "field": "recordTags",
                            "value": "{{vars.record.vendor}}",
                            "_value": "{{vars.record.vendor}}",
                            "operator": "in"
                        }
                    ],
                    "__selectFields": [
                        "kEVAlerts",
                        "iCSAdvisories"
                    ]
                },
                "module": "c_v_es?$limit=5000&$relationships=true&$fsr_max_relation_count=5000",
                "checkboxFields": true,
                "step_variables": {
                    "cVEIRI": "{{vars.steps.Get_CVEs_By_Vendor | json_query('[*][\"@id\"][]') | unique }}",
                    "kEVAlertIRI": "{{vars.steps.Get_CVEs_By_Vendor | json_query('[*][\"kEVAlerts\"][][][\"@id\"][]') | unique}}",
                    "iCSAdvisoryIRI": "{{vars.steps.Get_CVEs_By_Vendor | json_query('[*][\"iCSAdvisories\"][][][\"@id\"][]') | unique}}"
                }
            },
            "status": null,
            "top": "300",
            "left": "125",
            "stepType": "\/api\/3\/workflow_step_types\/b593663d-7d13-40ce-a3a3-96dece928770",
            "group": null,
            "uuid": "b061f2a4-cdab-46db-97a2-3114cd33d629"
        },
        {
            "@type": "WorkflowStep",
            "name": "Start",
            "description": null,
            "arguments": {
                "resource": "assets",
                "resources": [
                    "assets"
                ],
                "step_variables": {
                    "input": {
                        "params": [],
                        "records": [
                            "{{vars.input.records[0]}}"
                        ]
                    }
                },
                "fieldbasedtrigger": {
                    "sort": [],
                    "limit": 30,
                    "logic": "AND",
                    "filters": [
                        {
                            "type": "array",
                            "field": "recordTags",
                            "value": [
                                "\/api\/3\/tags\/Nozomi"
                            ],
                            "module": "recordTags",
                            "display": null,
                            "operator": "in",
                            "template": "tags",
                            "OPERATOR_KEY": "$",
                            "previousOperator": "in",
                            "previousTemplate": "tags"
                        }
                    ]
                }
            },
            "status": null,
            "top": "30",
            "left": "125",
            "stepType": "\/api\/3\/workflow_step_types\/ea155646-3821-4542-9702-b246da430a8d",
            "group": null,
            "uuid": "460300eb-79e1-4d8a-8963-75e4eccdfa98"
        },
        {
            "@type": "WorkflowStep",
            "name": "Summary On Asset",
            "description": null,
            "arguments": {
                "when": "{{vars.steps.Get_CVEs_By_Vendor | length > 0}}",
                "params": {
                    "value": "<p>KEV Alert for Asset vendor: <span class=\"badge badge-pill badge-danger\" style=\"background: #009d00; color: #fff;\">{{vars.record.vendor}}<\/span> has been found. So correlated this asset with KEV Alert, ICS Advisories and CVEs.<\/p>\n<p>{% if vars.kEVAlertIRI | length > 0 %}<\/p>\n<h4>KEV Alert<\/h4>\n<p>{% for item in vars.kEVAlertIRI %} {{loop.index}}: <a href=\"\/modules\/k_e_v_alerts\/{{item.split('\/')[-1]}}\" target=\"_blank\" rel=\"noopener\">{{(item | fromIRI).title}} <\/a><br \/>{% endfor %}<\/p>\n<p>{% endif %}<\/p>"
                },
                "version": "3.2.3",
                "connector": "cyops_utilities",
                "operation": "format_richtext",
                "operationTitle": "Utils: Format as RichText (Markdown)",
                "step_variables": []
            },
            "status": null,
            "top": "570",
            "left": "125",
            "stepType": "\/api\/3\/workflow_step_types\/0109f35d-090b-4a2b-bd8a-94cbc3508562",
            "group": null,
            "uuid": "26e975a7-69d2-4c5c-a26d-954ac85da5f2"
        },
        {
            "@type": "WorkflowStep",
            "name": "Update Asset With KEV Alert_ICS Advisory_CVEs",
            "description": null,
            "arguments": {
                "when": "{{vars.steps.Get_CVEs_By_Vendor | length > 0}}",
                "resource": {
                    "__link": {
                        "cVEs": "{{vars.cVEIRI}}",
                        "kEVAlerts": "{{vars.kEVAlertIRI}}",
                        "iCSAdvisories": "{{vars.iCSAdvisoryIRI}}"
                    }
                },
                "operation": "Append",
                "collection": "{{vars.record[\"@id\"]}}",
                "__recommend": [],
                "collectionType": "\/api\/3\/assets",
                "fieldOperation": {
                    "protocol": "Append"
                },
                "step_variables": []
            },
            "status": null,
            "top": "435",
            "left": "125",
            "stepType": "\/api\/3\/workflow_step_types\/b593663d-7d13-40ce-a3a3-96dece928722",
            "group": null,
            "uuid": "4a3b2798-ea48-44c4-b4de-5606dcecaeac"
        }
    ],
    "routes": [
        {
            "@type": "WorkflowRoute",
            "name": "Configuration -> Get KEV Alert",
            "targetStep": "\/api\/3\/workflow_steps\/b061f2a4-cdab-46db-97a2-3114cd33d629",
            "sourceStep": "\/api\/3\/workflow_steps\/0ae118b4-4f4c-488b-96f7-c694860302dc",
            "label": null,
            "isExecuted": false,
            "group": null,
            "uuid": "0e68bbd4-ba7e-4029-8478-359fb7f03bea"
        },
        {
            "@type": "WorkflowRoute",
            "name": "Get KEV Alert -> Update Asset With KEV Alert_ICS Advisory_CVEs",
            "targetStep": "\/api\/3\/workflow_steps\/4a3b2798-ea48-44c4-b4de-5606dcecaeac",
            "sourceStep": "\/api\/3\/workflow_steps\/b061f2a4-cdab-46db-97a2-3114cd33d629",
            "label": null,
            "isExecuted": false,
            "group": null,
            "uuid": "5a8b84f7-3b3a-45fe-b4ee-187359eacfa0"
        },
        {
            "@type": "WorkflowRoute",
            "name": "Start -> Configuration",
            "targetStep": "\/api\/3\/workflow_steps\/0ae118b4-4f4c-488b-96f7-c694860302dc",
            "sourceStep": "\/api\/3\/workflow_steps\/460300eb-79e1-4d8a-8963-75e4eccdfa98",
            "label": null,
            "isExecuted": false,
            "group": null,
            "uuid": "5b490e1f-588f-43c8-b525-554d25315717"
        },
        {
            "@type": "WorkflowRoute",
            "name": "Summary On Asset -> Add Comment",
            "targetStep": "\/api\/3\/workflow_steps\/b8ad6c76-96fc-4ccb-93ae-83caf52a807b",
            "sourceStep": "\/api\/3\/workflow_steps\/26e975a7-69d2-4c5c-a26d-954ac85da5f2",
            "label": null,
            "isExecuted": false,
            "group": null,
            "uuid": "85dbf1b2-ecd2-4cab-a443-3d8be87192d4"
        },
        {
            "@type": "WorkflowRoute",
            "name": "Update Asset With KEV Alert_ICS Advisory_CVEs -> Summary On Asset",
            "targetStep": "\/api\/3\/workflow_steps\/26e975a7-69d2-4c5c-a26d-954ac85da5f2",
            "sourceStep": "\/api\/3\/workflow_steps\/4a3b2798-ea48-44c4-b4de-5606dcecaeac",
            "label": null,
            "isExecuted": false,
            "group": null,
            "uuid": "76729df6-cd75-41e6-9527-39bb88aafd19"
        }
    ],
    "groups": [],
    "priority": "\/api\/3\/picklists\/2b563c61-ae2c-41c0-a85a-c9709585e3f2",
    "uuid": "5d689b69-d4a1-49f8-b0e3-d92993f77218",
    "owners": [],
    "isPrivate": false,
    "deletedAt": null,
    "recordTags": [
        "PostCreate",
        "Alert",
        "KEV",
        "Nozomi"
    ]
}